typsio/__init__.py
typsio/gen.py
typsio/rpc.py
typsio-0.1.0.dist-info/METADATA
typsio-0.1.0.dist-info/WHEEL
typsio-0.1.0.dist-info/entry_points.txt
typsio-0.1.0.dist-info/RECORD
