Metadata-Version: 2.4
Name: typsio
Version: 0.1.0
Summary: A type-safe RPC and event library for python-socketio.
Project-URL: Homepage, https://github.com/xcantloadx/typsio
Project-URL: Bug Tracker, https://github.com/xcantloadx/typsio/issues
Author-email: XcantloadX <318899697@qq.com>
Classifier: Framework :: AsyncIO
Classifier: License :: OSI Approved :: MIT License
Classifier: Operating System :: OS Independent
Classifier: Programming Language :: Python :: 3
Classifier: Topic :: Internet :: WWW/HTTP :: Dynamic Content
Requires-Python: >=3.8
Requires-Dist: pydantic>=2.0.0
Requires-Dist: python-socketio>=5.0.0
